dsppkeras
