Metadata-Version: 1.1
Name: DSPP-Keras
Version: 0.0.3
Summary: Integration of DSPP database with Keral Machine Learning Library
Home-page: https://github.com/PeptoneInc/dspp-keras
Author: Jan Domanski
Author-email: jan@peptone.io
License: MIT
Download-URL: https://github.com/PeptoneInc/dspp-keras/archive/v0.0.3.tar.gz
Platform: UNKNOWN
